<?xml version="1.0" encoding="utf-8" ?>
<dwsync>
<file name="ond_320.html.mno" server="neuro.qi.fcen.uba.ar" local="129878120580000000" remote="125964005950000000" />
<file name="ond_319.html.mno" server="neuro.qi.fcen.uba.ar" local="129878120250000000" remote="125964005940000000" />
<file name="ond_318.html.mno" server="neuro.qi.fcen.uba.ar" local="129878119820000000" remote="125964005940000000" />
<file name="ond_317.html.mno" server="neuro.qi.fcen.uba.ar" local="130081874230000000" remote="125964005930000000" />
<file name="ond_316.html.mno" server="neuro.qi.fcen.uba.ar" local="129652440840000000" remote="125964005930000000" />
<file name="ond_315.html.mno" server="neuro.qi.fcen.uba.ar" local="130081854200000000" remote="125964005920000000" />
<file name="ond_314.html.mno" server="neuro.qi.fcen.uba.ar" local="129878118770000000" remote="125964005910000000" />
<file name="ond_313.html.mno" server="neuro.qi.fcen.uba.ar" local="129878118430000000" remote="125964005910000000" />
<file name="ond_3_14.html.mno" server="neuro.qi.fcen.uba.ar" local="130218319959790747" remote="125964005960000000" />
<file name="ond_3_15.html.mno" server="neuro.qi.fcen.uba.ar" local="130219500834337159" remote="125964005970000000" />
<file name="ond_3_16.html.mno" server="neuro.qi.fcen.uba.ar" local="129665308234757871" remote="125964005980000000" />
<file name="ond_3_20.html.mno" server="neuro.qi.fcen.uba.ar" local="130218429109139685" remote="125964006000000000" />
<file name="ond_3_13.html.mno" server="neuro.qi.fcen.uba.ar" local="130218322369968601" remote="125964005960000000" />
<file name="ond_3_17.html.mno" server="neuro.qi.fcen.uba.ar" local="130083733124531643" remote="125964005980000000" />
<file name="ond_3_18.html.mno" server="neuro.qi.fcen.uba.ar" local="129878711284301631" remote="125964005990000000" />
<file name="ond_3_19.html.mno" server="neuro.qi.fcen.uba.ar" local="129878711710032229" remote="125964005990000000" />
</dwsync>